torchext/__init__.py
torchext/config.py
torchext/data.py
torchext/utils.py
torchext-0.0.6.dist-info/LICENSE
torchext-0.0.6.dist-info/METADATA
torchext-0.0.6.dist-info/WHEEL
torchext-0.0.6.dist-info/top_level.txt
torchext-0.0.6.dist-info/RECORD
