Metadata-Version: 2.1
Name: torchext
Version: 0.0.6
Summary: A PyTorch extension library for easy experiments
Home-page: https://github.com/yongjincho/torchext
Author: Yongjin Cho
Author-email: yongjin.cho@gmail.com
License: Apache 2.0
Platform: UNKNOWN
Classifier: Development Status :: 2 - Pre-Alpha
Classifier: Intended Audience :: Developers
Classifier: Intended Audience :: Science/Research
Classifier: License :: OSI Approved :: Apache Software License
Classifier: Topic :: Scientific/Engineering :: Artificial Intelligence
Requires-Dist: tensorboardX
Requires-Dist: PyYAML
